elib_miz/__init__.py
elib_miz/dummy_miz.py
elib_miz/exc.py
elib_miz/mission.py
elib_miz/mission_time.py
elib_miz/miz.py
elib_miz/sltp.py
elib_miz/static.py
elib_miz/validator.py
test/__init__.py
test/conftest.py
test/test_mission_time.py
test/test_miz.py
test/test_sltp.py
test/test_files/SDCM_1.4.0.127_csar.miz
test/test_files/TRG_KA50.miz
test/test_files/TRMT_2.4.0.miz
test/test_files/TRMT_5.1.0-OVC-171220.miz
test/test_files/TRMT_6.4.3.miz
test/test_files/TRM_0.1.0.159_edit.miz
test/test_files/all_objects.miz
test/test_files/bad_zip_file.miz
test/test_files/clients.miz
test/test_files/duplicate_group_id.miz
test/test_files/empty.miz
test/test_files/missing_files.miz
test/test_files/radios.miz
test/test_files/radios2.miz
test/test_files/test_158.miz
test/test_files/test_252.miz
test/test_files/test_253.miz
test/test_files/test_dust.miz
test/test_files/time.miz
test/test_files/weather.miz
test/test_files/weather_output.miz
test/test_files/empty/mission
test/test_files/empty/options
test/test_files/empty/warehouses
test/test_files/empty/l10n/DEFAULT/dictionary
test/test_files/empty/l10n/DEFAULT/mapResource
test/test_files/sltp/diff/dic1
test/test_files/sltp/diff/dic2
test/test_files/sltp/diff/dic3
test/test_files/sltp/diff/dic4
test/test_files/sltp/fail/dic1
test/test_files/sltp/fail/dic2
test/test_files/sltp/fail/dic3
test/test_files/sltp/long/mis1
test/test_files/sltp/pass/dic1
test/test_files/sltp/pass/dic2
test/test_files/sltp/pass/dic3
test/test_files/sltp/pass/dic4
test/test_files/sltp/pass/dic5
test/test_mission/test_base_mission_object.py
test/test_mission/test_coalition.py
test/test_mission/test_country.py
test/test_mission/test_datetime.py
test/test_mission/test_group.py
test/test_mission/test_large.py
test/test_mission/test_mission.py
test/test_mission/test_mission_weather.py
test/test_mission/test_miz_file.py
test/test_mission/test_radios.py
test/test_mission/test_start_time.py
test/test_mission/test_unit.py
elib_miz-2018.10.21.1.dist-info/AUTHORS.md
elib_miz-2018.10.21.1.dist-info/LICENSE
elib_miz-2018.10.21.1.dist-info/METADATA
elib_miz-2018.10.21.1.dist-info/WHEEL
elib_miz-2018.10.21.1.dist-info/top_level.txt
elib_miz-2018.10.21.1.dist-info/RECORD
